{"nodes": [{"id": "c_users_eloir_documents_projectes_mypr_mypr_fr_routes_json", "label": "_routes.json", "file_type": "code", "source_file": "C:\\Users\\eloir\\Documents\\projectes\\myPR\\mypr-fr\\_routes.json", "source_location": "L1"}, {"id": "mypr_fr_routes_version", "label": "version", "file_type": "code", "source_file": "C:\\Users\\eloir\\Documents\\projectes\\myPR\\mypr-fr\\_routes.json", "source_location": "L2"}, {"id": "mypr_fr_routes_include", "label": "include", "file_type": "code", "source_file": "C:\\Users\\eloir\\Documents\\projectes\\myPR\\mypr-fr\\_routes.json", "source_location": "L3"}, {"id": "mypr_fr_routes_exclude", "label": "exclude", "file_type": "code", "source_file": "C:\\Users\\eloir\\Documents\\projectes\\myPR\\mypr-fr\\_routes.json", "source_location": "L4"}, {"id": "mypr_fr_routes_routes", "label": "routes", "file_type": "code", "source_file": "C:\\Users\\eloir\\Documents\\projectes\\myPR\\mypr-fr\\_routes.json", "source_location": "L11"}], "edges": [{"source": "c_users_eloir_documents_projectes_mypr_mypr_fr_routes_json", "target": "mypr_fr_routes_version", "relation": "contains", "confidence": "EXTRACTED", "source_file": "C:\\Users\\eloir\\Documents\\projectes\\myPR\\mypr-fr\\_routes.json", "source_location": "L2", "weight": 1.0}, {"source": "c_users_eloir_documents_projectes_mypr_mypr_fr_routes_json", "target": "mypr_fr_routes_include", "relation": "contains", "confidence": "EXTRACTED", "source_file": "C:\\Users\\eloir\\Documents\\projectes\\myPR\\mypr-fr\\_routes.json", "source_location": "L3", "weight": 1.0}, {"source": "mypr_fr_routes_include", "target": "ref", "relation": "extends", "confidence": "EXTRACTED", "source_file": "C:\\Users\\eloir\\Documents\\projectes\\myPR\\mypr-fr\\_routes.json", "source_location": "L3", "weight": 1.0, "context": "import"}, {"source": "c_users_eloir_documents_projectes_mypr_mypr_fr_routes_json", "target": "mypr_fr_routes_exclude", "relation": "contains", "confidence": "EXTRACTED", "source_file": "C:\\Users\\eloir\\Documents\\projectes\\myPR\\mypr-fr\\_routes.json", "source_location": "L4", "weight": 1.0}, {"source": "mypr_fr_routes_exclude", "target": "ref_assets", "relation": "extends", "confidence": "EXTRACTED", "source_file": "C:\\Users\\eloir\\Documents\\projectes\\myPR\\mypr-fr\\_routes.json", "source_location": "L4", "weight": 1.0, "context": "import"}, {"source": "mypr_fr_routes_exclude", "target": "ref_headers", "relation": "extends", "confidence": "EXTRACTED", "source_file": "C:\\Users\\eloir\\Documents\\projectes\\myPR\\mypr-fr\\_routes.json", "source_location": "L4", "weight": 1.0, "context": "import"}, {"source": "mypr_fr_routes_exclude", "target": "ref_redirects", "relation": "extends", "confidence": "EXTRACTED", "source_file": "C:\\Users\\eloir\\Documents\\projectes\\myPR\\mypr-fr\\_routes.json", "source_location": "L4", "weight": 1.0, "context": "import"}, {"source": "mypr_fr_routes_exclude", "target": "ref_favicon_ico", "relation": "extends", "confidence": "EXTRACTED", "source_file": "C:\\Users\\eloir\\Documents\\projectes\\myPR\\mypr-fr\\_routes.json", "source_location": "L4", "weight": 1.0, "context": "import"}, {"source": "mypr_fr_routes_exclude", "target": "ref_robots_txt", "relation": "extends", "confidence": "EXTRACTED", "source_file": "C:\\Users\\eloir\\Documents\\projectes\\myPR\\mypr-fr\\_routes.json", "source_location": "L4", "weight": 1.0, "context": "import"}, {"source": "c_users_eloir_documents_projectes_mypr_mypr_fr_routes_json", "target": "mypr_fr_routes_routes", "relation": "contains", "confidence": "EXTRACTED", "source_file": "C:\\Users\\eloir\\Documents\\projectes\\myPR\\mypr-fr\\_routes.json", "source_location": "L11", "weight": 1.0}]}